odoo/addons/l10n_pe_toponym/README.rst
odoo/addons/l10n_pe_toponym/__init__.py
odoo/addons/l10n_pe_toponym/__manifest__.py
odoo/addons/l10n_pe_toponym/gen_src/README.rst
odoo/addons/l10n_pe_toponym/gen_src/__init__.py
odoo/addons/l10n_pe_toponym/gen_src/gen_data_toponym.py
odoo/addons/l10n_pe_toponym/gen_src/rptUbigeo.xls
odoo/addons/l10n_pe_toponym/i18n/es_PE.po
odoo/addons/l10n_pe_toponym/i18n/l10n_pe_toponym.pot
odoo/addons/l10n_pe_toponym/models/__init__.py
odoo/addons/l10n_pe_toponym/models/l10n_pe_toponym.py
odoo/addons/l10n_pe_toponym/readme/CONTRIBUTORS.rst
odoo/addons/l10n_pe_toponym/readme/DESCRIPTION.rst
odoo/addons/l10n_pe_toponym/security/ir.model.access.csv
odoo/addons/l10n_pe_toponym/static/description/icon.png
odoo/addons/l10n_pe_toponym/static/description/index.html
odoo/addons/l10n_pe_toponym/test/__init__.py
odoo/addons/l10n_pe_toponym/test/test_l10n_pe_toponym.py
odoo/addons/l10n_pe_toponym/views/l10n_pe_toponym_views.xml
odoo/addons/l10n_pe_toponym/wizard/__init__.py
odoo/addons/l10n_pe_toponym/wizard/l10n_pe_toponym_wizard.py
odoo/addons/l10n_pe_toponym/wizard/l10n_pe_toponym_wizard.xml
odoo/addons/l10n_pe_toponym/wizard/ubigeo_data.xml
odoo12_addon_l10n_pe_toponym-12.0.1.0.0.99.dev2.dist-info/METADATA
odoo12_addon_l10n_pe_toponym-12.0.1.0.0.99.dev2.dist-info/WHEEL
odoo12_addon_l10n_pe_toponym-12.0.1.0.0.99.dev2.dist-info/top_level.txt
odoo12_addon_l10n_pe_toponym-12.0.1.0.0.99.dev2.dist-info/RECORD
